data_loader/__init__.py
data_loader/main.py
refinitiv-data-loader/__init__.py
refinitiv-data-loader/main.py
refinitiv_data_loader-0.0.3.dist-info/licenses/LICENSE
refinitiv_data_loader-0.0.3.dist-info/METADATA
refinitiv_data_loader-0.0.3.dist-info/WHEEL
refinitiv_data_loader-0.0.3.dist-info/entry_points.txt
refinitiv_data_loader-0.0.3.dist-info/top_level.txt
refinitiv_data_loader-0.0.3.dist-info/RECORD
