Metadata-Version: 2.4
Name: refinitiv-data-loader
Version: 0.0.3
Author: Jonathan Willert
License-File: LICENSE
Requires-Dist: pandas
Requires-Dist: polars
Requires-Dist: requests
Dynamic: author
Dynamic: description
Dynamic: description-content-type
Dynamic: license-file
Dynamic: requires-dist
